snorkel/__init__.py
snorkel/version.py
snorkel/analysis/__init__.py
snorkel/analysis/error_analysis.py
snorkel/analysis/metrics.py
snorkel/analysis/scorer.py
snorkel/augmentation/__init__.py
snorkel/augmentation/tf.py
snorkel/augmentation/apply/__init__.py
snorkel/augmentation/apply/core.py
snorkel/augmentation/apply/pandas.py
snorkel/augmentation/policy/__init__.py
snorkel/augmentation/policy/core.py
snorkel/augmentation/policy/sampling.py
snorkel/classification/__init__.py
snorkel/classification/data.py
snorkel/classification/loss.py
snorkel/classification/multitask_classifier.py
snorkel/classification/task.py
snorkel/classification/utils.py
snorkel/classification/training/__init__.py
snorkel/classification/training/trainer.py
snorkel/classification/training/loggers/__init__.py
snorkel/classification/training/loggers/checkpointer.py
snorkel/classification/training/loggers/log_manager.py
snorkel/classification/training/loggers/log_writer.py
snorkel/classification/training/loggers/tensorboard_writer.py
snorkel/classification/training/schedulers/__init__.py
snorkel/classification/training/schedulers/scheduler.py
snorkel/classification/training/schedulers/sequential_scheduler.py
snorkel/classification/training/schedulers/shuffled_scheduler.py
snorkel/contrib/__init__.py
snorkel/labeling/__init__.py
snorkel/labeling/analysis.py
snorkel/labeling/utils.py
snorkel/labeling/apply/__init__.py
snorkel/labeling/apply/core.py
snorkel/labeling/apply/dask.py
snorkel/labeling/apply/pandas.py
snorkel/labeling/apply/spark.py
snorkel/labeling/lf/__init__.py
snorkel/labeling/lf/core.py
snorkel/labeling/lf/nlp.py
snorkel/labeling/lf/nlp_spark.py
snorkel/labeling/model/__init__.py
snorkel/labeling/model/base_labeler.py
snorkel/labeling/model/baselines.py
snorkel/labeling/model/graph_utils.py
snorkel/labeling/model/label_model.py
snorkel/labeling/model/logger.py
snorkel/map/__init__.py
snorkel/map/core.py
snorkel/map/spark.py
snorkel/preprocess/__init__.py
snorkel/preprocess/core.py
snorkel-0.10.0.dist-info/LICENSE
snorkel-0.10.0.dist-info/METADATA
snorkel-0.10.0.dist-info/WHEEL
snorkel-0.10.0.dist-info/top_level.txt
snorkel-0.10.0.dist-info/RECORD
