Metadata-Version: 2.1
Name: snorkel
Version: 0.10.0
Summary: A system for quickly generating training data with weak supervision
Home-page: https://github.com/snorkel-team/snorkel
License: Apache License 2.0
Project-URL: Homepage, https://snorkel.org
Project-URL: Source, https://github.com/snorkel-team/snorkel/
Project-URL: Bug Reports, https://github.com/snorkel-team/snorkel/issues
Project-URL: Citation, https://doi.org/10.14778/3157794.3157797
Keywords: machine-learning ai weak-supervision
Platform: UNKNOWN
Classifier: Intended Audience :: Science/Research
Classifier: Topic :: Scientific/Engineering :: Information Analysis
Classifier: License :: OSI Approved :: Apache Software License
Classifier: Programming Language :: Python :: 3
Requires-Python: >=3.11
License-File: LICENSE
Requires-Dist: munkres (>=1.0.6)
Requires-Dist: numpy (>=1.24.0)
Requires-Dist: scipy (>=1.2.0)
Requires-Dist: pandas (>=1.0.0)
Requires-Dist: tqdm (>=4.33.0)
Requires-Dist: scikit-learn (>=0.20.2)
Requires-Dist: torch (>=1.2.0)
Requires-Dist: tensorboard (>=2.13.0)
Requires-Dist: protobuf (>=3.19.6)
Requires-Dist: networkx (>=2.2)
